geminikit/__init__.py
geminikit/asynic_gemini.py
geminikit/gemini.py
geminikit/headers.py
geminikit/helpers.py
geminikit-1.2.1.dist-info/LICENSE
geminikit-1.2.1.dist-info/METADATA
geminikit-1.2.1.dist-info/WHEEL
geminikit-1.2.1.dist-info/top_level.txt
geminikit-1.2.1.dist-info/RECORD
